.gitignore
LICENSE
README.md
README.txt
TODO
screenshot.png
setup.py
shadowsocks-gtk.desktop
stdeb.cfg
shadowsocks_gtk/__init__.py
shadowsocks_gtk/encrypt.py
shadowsocks_gtk/encrypt_salsa20.py
shadowsocks_gtk/local.py
shadowsocks_gtk/shadowsocks.png
shadowsocks_gtk/shadowsocks.py
shadowsocks_gtk/utils.py
shadowsocks_gtk.egg-info/PKG-INFO
shadowsocks_gtk.egg-info/SOURCES.txt
shadowsocks_gtk.egg-info/dependency_links.txt
shadowsocks_gtk.egg-info/entry_points.txt
shadowsocks_gtk.egg-info/top_level.txt
shadowsocks_gtk.egg-info/zip-safe
shadowsocks_gtk/locale/shadowsocks_gtk_en.mo
shadowsocks_gtk/locale/shadowsocks_gtk_zh.mo
shadowsocks_gtk/locale/en_US/LC_MESSAGES/shadowsocks_gtk.mo
shadowsocks_gtk/locale/zh_CN/LC_MESSAGES/shadowsocks_gtk.mo