Metadata-Version: 1.1
Name: shadowsocks-gtk
Version: 0.1
Summary: ShadowSocks Gtk Client
Home-page: https://github.com/apporc/shadowsocks-gtk
Author: apporc
Author-email: apporc@gmail.com
License: http://opensource.org/licenses/MIT
Platform: UNKNOWN
Classifier: Development Status :: 3 - Alpha
Classifier: Environment :: Console
Classifier: Environment :: X11 Applications
Classifier: Environment :: X11 Applications :: Gnome
Classifier: Environment :: X11 Applications :: GTK
Classifier: Framework :: Twisted
Classifier: Intended Audience :: End Users/Desktop
Classifier: Intended Audience :: Developers
Classifier: Intended Audience :: System Administrators
Classifier: License :: OSI Approved :: MIT License
Classifier: Natural Language :: Chinese (Simplified)
Classifier: Natural Language :: English
Classifier: Operating System :: POSIX
Classifier: Operating System :: POSIX :: Linux
Classifier: Programming Language :: Python :: 2
Classifier: Programming Language :: Python :: 2.7
Classifier: Topic :: Internet
